[
  {
    "id": 1,
    "favorite": false,
    "image": "/assets/images/image.png",
    "title": "Monitor LED 27'' Gamer Curvo Samsung 1920 x 1080 FHD 240 Hz HDMI, DP, Gsync Série CRG50",
    "oldPrice": 2323.1,
    "newPrice": 1234.0,
    "nInstalments": 10,
    "priceInstalments": 123.4,
    "added": false
  },

  {
    "id": 2,
    "favorite": false,
    "image": "/assets/images/image.png",
    "title": "Smartphone Galaxy A03s Tela 6.5 64 Gb 4 Gb Ram Azul Samsung",
    "oldPrice": 999.1,
    "newPrice": 888.0,
    "nInstalments": 3,
    "priceInstalments": 132.4,
    "added": false
  },

  {
    "id": 3,
    "favorite": false,
    "image": "/assets/images/image3.png",
    "title": "Produto de teste para texto mais curto. Sem imagem",
    "oldPrice": 23.1,
    "newPrice": 12.0,
    "nInstalments": 1,
    "priceInstalments": 12.4,
    "added": false
  },

  {
    "id": 4,
    "favorite": false,
    "image": "/assets/images/image4.png",
    "title": "Produto com descrição um pouco maior, mas sem imagem de produto e sem número de parcelas",
    "oldPrice": 23.1,
    "newPrice": 12.0,
    "nInstalments": 1,
    "priceInstalments": 12.4,
    "added": false
  }
]
